MANIFEST.in
README.md
setup.py
json_manipulate/__init__.py
json_manipulate/json_manipulate.py
json_manipulate.egg-info/PKG-INFO
json_manipulate.egg-info/SOURCES.txt
json_manipulate.egg-info/dependency_links.txt
json_manipulate.egg-info/entry_points.txt
json_manipulate.egg-info/not-zip-safe
json_manipulate.egg-info/top_level.txt