Metadata-Version: 1.0
Name: json-manipulate
Version: 0.1
Summary: Manipulate JSON strings from the command line.
Home-page: http://github.com/dporru/json_manipulate
Author: Daan Porru
Author-email: daanporru@gmail.com
License: GPLv3
Platform: UNKNOWN
